CHANGES.txt
CONTRIBUTORS.txt
README.txt
bootstrap.py
buildout.cfg
setup.cfg
setup.py
collective/__init__.py
collective.recipe.bootstrap.egg-info/PKG-INFO
collective.recipe.bootstrap.egg-info/SOURCES.txt
collective.recipe.bootstrap.egg-info/dependency_links.txt
collective.recipe.bootstrap.egg-info/entry_points.txt
collective.recipe.bootstrap.egg-info/namespace_packages.txt
collective.recipe.bootstrap.egg-info/not-zip-safe
collective.recipe.bootstrap.egg-info/requires.txt
collective.recipe.bootstrap.egg-info/top_level.txt
collective/recipe/__init__.py
collective/recipe/bootstrap/__init__.py
collective/recipe/bootstrap/tests/__init__.py
collective/recipe/bootstrap/tests/test_docs.py