Metadata-Version: 1.0
Name: collective.recipe.bootstrap
Version: 1.0
Summary: This recipe makes it easy to keep your buildout's bootstrap.py file up to date.
Home-page: UNKNOWN
Author: Alex Clark
Author-email: aclark@aclark.net
License: ZPL
Keywords: buildout
Platform: UNKNOWN
Classifier: Framework :: Buildout
Classifier: Intended Audience :: Developers
Classifier: Topic :: Software Development :: Build Tools
Classifier: Topic :: Software Development :: Libraries :: Python Modules
Classifier: License :: OSI Approved :: Zope Public License
